{
  "search_metadata": {
    "id": "",
    "status": "Success",
    "json_endpoint": "",
    "created_at": "2020-01-21 22:46:23 UTC",
    "processed_at": "2020-01-21 22:46:23 UTC",
    "google_url": "https://www.google.com/search?q=office+supplies+reno&oq=office+supplies+reno&sourceid=chrome&ie=UTF-8",
    "raw_html_file": "",
    "total_time_taken": 2.86
  },
  "search_parameters": {
    "engine": "google",
    "q": "office supplies reno",
    "google_domain": "google.com",
    "device": "desktop"
  },
  "search_information": {
    "organic_results_state": "Results for exact spelling",
    "total_results": 53600000,
    "time_taken_displayed": 0.43,
    "query_displayed": "office supplies reno"
  },
  "local_map": {
    "link": "https://www.google.com/search?q=office+supplies+reno&npsic=0&rflfq=1&rldoc=1&rlha=0&rllag=39519788,-119831022,3056&tbm=lcl&sa=X&ved=2ahUKEwi989fr4pXnAhVowTgGHdQYCwgQtgN6BAgLEAU",
    "image": "data:image/gif;base64,R0lGODlhAQABAIAAAP///////yH5BAEKAAEALAAAAAABAAEAAAICTAEAOw==",
    "gps_coordinates": {
      "latitude": 39.519788,
      "longitude": -119.831022,
      "altitude": 3056
    }
  },
  "local_results": {
    "more_locations_link": "https://www.google.com/search?q=office+supplies+reno&npsic=0&rflfq=1&rldoc=1&rlha=0&rllag=39519788,-119831022,3056&tbm=lcl&sa=X&ved=2ahUKEwi989fr4pXnAhVowTgGHdQYCwgQjGp6BAgLEEY",
    "places": [
      {
        "position": 1,
        "title": "Discount Office Supply",
        "place_id": "3571843009872487075",
        "lsig": "AB86z5V1qI351B4AfF9ivv23VAJZ",
        "place_id_search": "https://serpapi.com/search.json?device=desktop&engine=google&google_domain=google.com&lsig=AB86z5V1qI351B4AfF9ivv23VAJZ&ludocid=3571843009872487075&q=office+supplies+reno&tbm=lcl&token=0f74523d398ae729",
        "rating": 4.9,
        "reviews": 15,
        "type": "Office supply store",
        "hours": "Open ⋅ Closes 6PM · (775) 332-3290",
        "address": "727 W 5th St",
        "thumbnail": "data:image/gif;base64,R0lGODlhAQABAIAAAP///////yH5BAEKAAEALAAAAAABAAEAAAICTAEAOw==",
        "gps_coordinates": {
          "latitude": 39.529705,
          "longitude": -119.82468820000001
        }
      },
      {
        "position": 2,
        "title": "Staples",
        "place_id": "12180339657525874860",
        "lsig": "AB86z5W9ibswvoWdFPTEHz-I7L-O",
        "place_id_search": "https://serpapi.com/search.json?device=desktop&engine=google&google_domain=google.com&lsig=AB86z5W9ibswvoWdFPTEHz-I7L-O&ludocid=12180339657525874860&q=office+supplies+reno&tbm=lcl&token=650cd4faa1a52df6",
        "rating": 4.2,
        "reviews": 62,
        "price": "$$",
        "type": "Office supply store",
        "address": "10350 N McCarran Blvd",
        "phone": "In Canyon Center",
        "description": "Brand-name electronics & office supplies",
        "thumbnail": "data:image/gif;base64,R0lGODlhAQABAIAAAP///////yH5BAEKAAEALAAAAAABAAEAAAICTAEAOw==",
        "gps_coordinates": {
          "latitude": 39.532665,
          "longitude": -119.8625268
        }
      },
      {
        "position": 3,
        "title": "Staples",
        "place_id": "16909059118377911331",
        "lsig": "AB86z5XqVoxme2KvxqxtAVo7qcBb",
        "place_id_search": "https://serpapi.com/search.json?device=desktop&engine=google&google_domain=google.com&lsig=AB86z5XqVoxme2KvxqxtAVo7qcBb&ludocid=16909059118377911331&q=office+supplies+reno&tbm=lcl&token=be0c754cf39525e5",
        "rating": 3.9,
        "reviews": 59,
        "price": "$$",
        "type": "Office supply store",
        "address": "355 E Plumb Ln",
        "phone": "In Shoppers Square",
        "description": "Brand-name electronics & office supplies",
        "thumbnail": "data:image/gif;base64,R0lGODlhAQABAIAAAP///////yH5BAEKAAEALAAAAAABAAEAAAICTAEAOw==",
        "gps_coordinates": {
          "latitude": 39.506911599999995,
          "longitude": -119.79951769999998
        }
      }
    ]
  },
  "knowledge_graph": {},
  "organic_results": [
    {
      "position": 1,
      "title": "Top 10 Best Office Supplies in Reno, NV - Last Updated ...",
      "link": "https://www.yelp.com/search?find_desc=Office+Supplies&find_loc=Reno%2C+NV",
      "displayed_link": "www.yelp.com › search › find_loc=Reno,+NV",
      "snippet": "Office Depot. 1.4 mi. 15 reviews. Discount Office Supply. 2.4 mi. 6 reviews. Office Depot. 6.1 mi. 5 reviews. Staples. 0.5 mi. 39 reviews. Office Plus. 4.2 mi. 2 reviews. Staples. 4.0 mi. 23 reviews. Office Depot. 4.2 mi. 11 reviews. Affordable Office Furniture and Supplies. 2.4 mi. 1 review.",
      "cached_page_link": "https://webcache.googleusercontent.com/search?q=cache:E1tqwIL0sC0J:https://www.yelp.com/search%3Ffind_desc%3DOffice%2BSupplies%26find_loc%3DReno%252C%2BNV+&cd=4&hl=en&ct=clnk&gl=us"
    },
    {
      "position": 2,
      "title": "Office Depot in RENO,NV - 4827 KIETZKE LANE",
      "link": "https://www.officedepot.com/storelocator/nv/reno/office-depot-3252/",
      "displayed_link": "www.officedepot.com › storelocator › reno › office-depot-3252",
      "snippet": "Staplers & Staples. Paper & Binder Clips. Scissors. Paper Punches & Cutters.",
      "cached_page_link": "https://webcache.googleusercontent.com/search?q=cache:3y6oa_ZNa_wJ:https://www.officedepot.com/storelocator/nv/reno/office-depot-3252/+&cd=5&hl=en&ct=clnk&gl=us"
    },
    {
      "position": 3,
      "title": "Office Depot in RENO,NV - 2990 NORTHTOWNE LN",
      "link": "https://www.officedepot.com/storelocator/nv/reno/office-depot-583/",
      "displayed_link": "www.officedepot.com › storelocator › reno › office-depot-583",
      "snippet": "Office Depot reno, NV Store #583. ... When you shop at my Office Depot® in Reno you’ll enjoy low prices on office supplies and products, including everything from paper, ink and toner, to the latest technology, cleaning and breakroom supplies and more. ... No matter how you shop, you’ll ...",
      "cached_page_link": "https://webcache.googleusercontent.com/search?q=cache:VSei88SYDKoJ:https://www.officedepot.com/storelocator/nv/reno/office-depot-583/+&cd=6&hl=en&ct=clnk&gl=us"
    },
    {
      "position": 4,
      "title": "Staples® Shoppers Square, Reno, 89502 | Store Details",
      "link": "https://stores.staples.com/nv/reno/355-e-plumb-lane",
      "displayed_link": "stores.staples.com › NV › Reno",
      "snippet": "Visit this Reno Staples® for office supplies & furniture, school supplies, printers, ink & toner, copy paper, computers, technology, and more.",
      "cached_page_link": "https://webcache.googleusercontent.com/search?q=cache:OjSMoAd6hpMJ:https://stores.staples.com/nv/reno/355-e-plumb-lane+&cd=7&hl=en&ct=clnk&gl=us"
    },
    {
      "position": 5,
      "title": "Affordable Office Supplies and Furniture | Reno,NV and Yuba ...",
      "link": "http://www.affordableof.com/",
      "displayed_link": "www.affordableof.com",
      "snippet": "Find everyday low prices on trusted brands like 3M, ACCO, HP, Brother, Post-it, Hammermill, Starbucks, Kleenex, Hon, Pentel, and Universal. Breakroom ...",
      "sitelinks": {
        "inline": [
          {
            "title": "Office Supplies",
            "link": "http://www.affordableof.com/Categories/Office-Supplies.aspx"
          },
          {
            "title": "Furniture",
            "link": "http://www.affordableof.com/Categories/Furniture.aspx"
          },
          {
            "title": "About Us Reno Nevada",
            "link": "http://www.affordableof.com/about-us/Reno-Nevada.aspx"
          },
          {
            "title": "Binders & Binding Supplies",
            "link": "http://www.affordableof.com/Categories/Office-Supplies/Binders-and-Binding-Supplies.aspx"
          }
        ]
      },
      "cached_page_link": "http://webcache.googleusercontent.com/search?q=cache:ySEfeFsTzWwJ:www.affordableof.com/+&cd=8&hl=en&ct=clnk&gl=us",
      "related_pages_link": "https://www.google.com/search?q=related:www.affordableof.com/+office+supplies+reno&tbo=1&sa=X&ved=2ahUKEwi989fr4pXnAhVowTgGHdQYCwgQHzAHegQIARAH"
    },
    {
      "position": 6,
      "title": "Community Office Solutions - Office Supplies Reno-Sparks ...",
      "link": "https://communityofficesolutions.com/",
      "displayed_link": "communityofficesolutions.com",
      "snippet": "Charity of the Month. Community Office Solutions will donate a portion of this month's purchases to: Learn More . free-shipping ...",
      "cached_page_link": "https://webcache.googleusercontent.com/search?q=cache:ugnlQY0kYZoJ:https://communityofficesolutions.com/+&cd=9&hl=en&ct=clnk&gl=us"
    },
    {
      "position": 7,
      "title": "Best 30 Office Supplies in Reno, NV with Reviews - YP.com",
      "link": "https://www.yellowpages.com/reno-nv/office-supplies",
      "displayed_link": "www.yellowpages.com › Reno, NV",
      "date": "66 results",
      "snippet": "Office Supplies in Reno on YP.com. See reviews, photos, directions, phone numbers and more for the best Office Equipment & Supplies in Reno, NV.",
      "cached_page_link": "https://webcache.googleusercontent.com/search?q=cache:Sv4qIl7zaZIJ:https://www.yellowpages.com/reno-nv/office-supplies+&cd=10&hl=en&ct=clnk&gl=us"
    },
    {
      "position": 8,
      "title": "Discount Office Supply - Reno, NV - Buy Nevada First",
      "link": "http://network.buynevadafirst.com/livelocalrenosparks/mem_discountoffice",
      "displayed_link": "network.buynevadafirst.com › livelocalrenosparks › mem_discountof...",
      "snippet": "We also offer free delivery in the Reno Sparks area and if you have an emergency ... work environment with our exceptional office products, furniture, and supplies.",
      "cached_page_link": "http://webcache.googleusercontent.com/search?q=cache:DnanjOutHxIJ:network.buynevadafirst.com/livelocalrenosparks/mem_discountoffice+&cd=11&hl=en&ct=clnk&gl=us"
    },
    {
      "position": 9,
      "title": "Reno Office Depot Weekly Ad Office Supplies - low prices on ...",
      "link": "https://officedepot.shoplocal.com/officedepotsd/weeklyad/category?storeid=2671247&cattreeid=5210648&fromsitemap=y",
      "displayed_link": "officedepot.shoplocal.com › officedepotsd › weeklyad › category",
      "snippet": "Reno Office Depot Weekly Ad Office Supplies - low prices on Office Supplies!"
    },
    {
      "position": 10,
      "title": "Office Plus of Nevada",
      "link": "http://www.officeplusnv.com/",
      "displayed_link": "www.officeplusnv.com",
      "snippet": "No information is available for this page.Learn why"
    }
  ],
  "related_search_boxes": [],
  "related_searches": [
    {
      "query": "office depot reno",
      "link": "https://www.google.com/search?q=office+depot+reno&sa=X&ved=2ahUKEwi989fr4pXnAhVowTgGHdQYCwgQ1QIoAHoECA0QAQ"
    },
    {
      "query": "staples reno",
      "link": "https://www.google.com/search?q=staples+reno&sa=X&ved=2ahUKEwi989fr4pXnAhVowTgGHdQYCwgQ1QIoAXoECA0QAg"
    },
    {
      "query": "office supplies near me",
      "link": "https://www.google.com/search?q=office+supplies+near+me&sa=X&ved=2ahUKEwi989fr4pXnAhVowTgGHdQYCwgQ1QIoAnoECA0QAw"
    },
    {
      "query": "office supply store near me",
      "link": "https://www.google.com/search?q=office+supply+store+near+me&sa=X&ved=2ahUKEwi989fr4pXnAhVowTgGHdQYCwgQ1QIoA3oECA0QBA"
    },
    {
      "query": "office depot near me",
      "link": "https://www.google.com/search?q=office+depot+near+me&sa=X&ved=2ahUKEwi989fr4pXnAhVowTgGHdQYCwgQ1QIoBHoECA0QBQ"
    },
    {
      "query": "office depot reno steamboat",
      "link": "https://www.google.com/search?q=office+depot+reno+steamboat&sa=X&ved=2ahUKEwi989fr4pXnAhVowTgGHdQYCwgQ1QIoBXoECA0QBg"
    },
    {
      "query": "staples near me",
      "link": "https://www.google.com/search?q=staples+near+me&sa=X&ved=2ahUKEwi989fr4pXnAhVowTgGHdQYCwgQ1QIoBnoECA0QBw"
    },
    {
      "query": "office max",
      "link": "https://www.google.com/search?q=office+max&sa=X&ved=2ahUKEwi989fr4pXnAhVowTgGHdQYCwgQ1QIoB3oECA0QCA"
    }
  ],
  "pagination": {
    "current": 1,
    "next": "https://www.google.com/search?q=office+supplies+reno&ei=QH8nXr3THuiC4-EP1LGsQA&start=10&sa=N&ved=2ahUKEwi989fr4pXnAhVowTgGHdQYCwgQ8NMDegQIDhA_",
    "other_pages": {
      "2": "https://www.google.com/search?q=office+supplies+reno&ei=QH8nXr3THuiC4-EP1LGsQA&start=10&sa=N&ved=2ahUKEwi989fr4pXnAhVowTgGHdQYCwgQ8tMDegQIDhAt",
      "3": "https://www.google.com/search?q=office+supplies+reno&ei=QH8nXr3THuiC4-EP1LGsQA&start=20&sa=N&ved=2ahUKEwi989fr4pXnAhVowTgGHdQYCwgQ8tMDegQIDhAv",
      "4": "https://www.google.com/search?q=office+supplies+reno&ei=QH8nXr3THuiC4-EP1LGsQA&start=30&sa=N&ved=2ahUKEwi989fr4pXnAhVowTgGHdQYCwgQ8tMDegQIDhAx",
      "5": "https://www.google.com/search?q=office+supplies+reno&ei=QH8nXr3THuiC4-EP1LGsQA&start=40&sa=N&ved=2ahUKEwi989fr4pXnAhVowTgGHdQYCwgQ8tMDegQIDhAz",
      "6": "https://www.google.com/search?q=office+supplies+reno&ei=QH8nXr3THuiC4-EP1LGsQA&start=50&sa=N&ved=2ahUKEwi989fr4pXnAhVowTgGHdQYCwgQ8tMDegQIDhA1",
      "7": "https://www.google.com/search?q=office+supplies+reno&ei=QH8nXr3THuiC4-EP1LGsQA&start=60&sa=N&ved=2ahUKEwi989fr4pXnAhVowTgGHdQYCwgQ8tMDegQIDhA3",
      "8": "https://www.google.com/search?q=office+supplies+reno&ei=QH8nXr3THuiC4-EP1LGsQA&start=70&sa=N&ved=2ahUKEwi989fr4pXnAhVowTgGHdQYCwgQ8tMDegQIDhA5",
      "9": "https://www.google.com/search?q=office+supplies+reno&ei=QH8nXr3THuiC4-EP1LGsQA&start=80&sa=N&ved=2ahUKEwi989fr4pXnAhVowTgGHdQYCwgQ8tMDegQIDhA7",
      "10": "https://www.google.com/search?q=office+supplies+reno&ei=QH8nXr3THuiC4-EP1LGsQA&start=90&sa=N&ved=2ahUKEwi989fr4pXnAhVowTgGHdQYCwgQ8tMDegQIDhA9"
    }
  },
  "serpapi_pagination": {
    "current": 1,
    "next_link": "https://serpapi.com/search.json?device=desktop&engine=google&google_domain=google.com&q=office+supplies+reno&start=10&token=0af4cb1b5bc67725",
    "next": "https://serpapi.com/search.json?device=desktop&engine=google&google_domain=google.com&q=office+supplies+reno&start=10&token=0af4cb1b5bc67725",
    "other_pages": {
      "2": "https://serpapi.com/search.json?device=desktop&engine=google&google_domain=google.com&q=office+supplies+reno&start=10&token=0af4cb1b5bc67725",
      "3": "https://serpapi.com/search.json?device=desktop&engine=google&google_domain=google.com&q=office+supplies+reno&start=20&token=0713fdbed8cdb3f5",
      "4": "https://serpapi.com/search.json?device=desktop&engine=google&google_domain=google.com&q=office+supplies+reno&start=30&token=6de7495d1ebd6e57",
      "5": "https://serpapi.com/search.json?device=desktop&engine=google&google_domain=google.com&q=office+supplies+reno&start=40&token=5b695b95709db22f",
      "6": "https://serpapi.com/search.json?device=desktop&engine=google&google_domain=google.com&q=office+supplies+reno&start=50&token=ba5b39934b868a95",
      "7": "https://serpapi.com/search.json?device=desktop&engine=google&google_domain=google.com&q=office+supplies+reno&start=60&token=432b2c9ef559339d",
      "8": "https://serpapi.com/search.json?device=desktop&engine=google&google_domain=google.com&q=office+supplies+reno&start=70&token=7d5728108eab1181",
      "9": "https://serpapi.com/search.json?device=desktop&engine=google&google_domain=google.com&q=office+supplies+reno&start=80&token=02da13a7e56db133",
      "10": "https://serpapi.com/search.json?device=desktop&engine=google&google_domain=google.com&q=office+supplies+reno&start=90&token=6a2d041a4354f581"
    }
  }
}