{
  "search_metadata": {
    "id": "",
    "status": "Success",
    "json_endpoint": "",
    "created_at": "2020-01-20 14:26:58 UTC",
    "processed_at": "2020-01-20 14:26:58 UTC",
    "google_url": "https://www.google.com/search?q=professional+seo+services&oq=professional+seo+services&sourceid=chrome&ie=UTF-8",
    "raw_html_file": "",
    "total_time_taken": 1.78
  },
  "search_parameters": {
    "engine": "google",
    "q": "professional seo services",
    "google_domain": "google.com",
    "device": "desktop"
  },
  "search_information": {
    "organic_results_state": "Results for exact spelling",
    "total_results": 301000000,
    "time_taken_displayed": 0.47,
    "query_displayed": "professional seo services"
  },
  "ads": [
    {
      "position": 1,
      "block_position": "bottom",
      "title": "Professional SEO company | Professional SEO agency‎",
      "link": "https://www.trustcorp.net/",
      "displayed_link": "www.trustcorp.net/💥",
      "tracking_link": "https://www.google.com/aclk?sa=l&ai=DChcSEwjIzNSssZLnAhUIu-wKHajDC1YYABAAGgJwag&sig=AOD64_3ro5ViByhSfG-OOxwogEh4nYyIgQ&q=&ved=2ahUKEwiPh82ssZLnAhXYi54KHdZNC_kQ0Qx6BAgUEAE&adurl=",
      "description": "Professional SEO company TrustCorp - proven track record in 27 countries. Professional SEO services for small, medium and enterprise business. US, UK, Canada, Australia. Services: SEO audit, niche analysis, keyword research, content, on-site SEO, backlinks.",
      "sitelinks": [
        {
          "title": "Professional SEO agency",
          "link": "https://www.trustcorp.net/?utm_source=google&utm_medium=cpc&utm_campaign=%7Bnetwork%7D&utm_content=%7Bcreative%7D&utm_term=%7Bkeyword%7D"
        },
        {
          "title": "SEO audit services",
          "link": "https://www.trustcorp.net/seo-audit-services?utm_source=google&utm_medium=cpc&utm_campaign=%7Bnetwork%7D&utm_content=%7Bcreative%7D&utm_term=%7Bkeyword%7D"
        },
        {
          "title": "Request a quote",
          "link": "https://www.trustcorp.net/?utm_source=google&utm_medium=cpc&utm_campaign=%7Bnetwork%7D&utm_content=%7Bcreative%7D&utm_term=%7Bkeyword%7D#rec103306853"
        },
        {
          "title": "Professional SEO services",
          "link": "https://www.trustcorp.net/?utm_source=google&utm_medium=cpc&utm_campaign=%7Bnetwork%7D&utm_content=%7Bcreative%7D&utm_term=%7Bkeyword%7D#rec144450820"
        }
      ]
    },
    {
      "position": 2,
      "block_position": "bottom",
      "title": "Professional SEO Services | Show Up Everywhere Leads Look‎",
      "link": "https://directiveconsulting.com/services/seo/",
      "displayed_link": "www.directiveconsulting.com/professional/seo-services",
      "tracking_link": "https://www.google.com/aclk?sa=l&ai=DChcSEwjIzNSssZLnAhUIu-wKHajDC1YYABAIGgJwag&sig=AOD64_3C8fCIzIFKVWv19Slc98QM9YB_nQ&q=&ved=2ahUKEwiPh82ssZLnAhXYi54KHdZNC_kQ0Qx6BAgTEAE&adurl=",
      "description": "89% More Hours on Your Account Compared to the Agency Average. Get A Custom Proposal Today. Own the Top of the Search Engine Results Page & Drive Quality Leads. Get A Custom Proposal. Clutch.co Global Leader. Chief Marketer Top Agency. Bing Partner.",
      "sitelinks": [
        {
          "title": "Case Studies",
          "link": "https://directiveconsulting.com/case-studies/"
        },
        {
          "title": "Get a Custom Proposal",
          "link": "https://directiveconsulting.com/get-quote/?_bt=%7Bcreative%7D&_bk=%7Bkeyword%7D&_bm=%7BmatchType%7D&_bn=%7Bnetwork%7D"
        },
        {
          "title": "SEO Services",
          "link": "https://directiveconsulting.com/services/seo/"
        },
        {
          "title": "PPC Services",
          "link": "https://directiveconsulting.com/services/ppc/"
        },
        {
          "title": "Content Marketing",
          "link": "https://directiveconsulting.com/services/content/"
        }
      ]
    }
  ],
  "local_map": {
    "link": "https://www.google.com/search?q=professional+seo+services&npsic=0&rflfq=1&rldoc=1&rlha=0&rllag=42548649,-114126980,27326&tbm=lcl&sa=X&ved=2ahUKEwiPh82ssZLnAhXYi54KHdZNC_kQtgN6BAgLEAQ",
    "image": "data:image/gif;base64,R0lGODlhAQABAIAAAP///////yH5BAEKAAEALAAAAAABAAEAAAICTAEAOw==",
    "gps_coordinates": {
      "latitude": 42.548649,
      "longitude": -114.12698,
      "altitude": 27326
    }
  },
  "local_results": {
    "more_locations_link": "https://www.google.com/search?q=professional+seo+services&npsic=0&rflfq=1&rldoc=1&rlha=0&rllag=42548649,-114126980,27326&tbm=lcl&sa=X&ved=2ahUKEwiPh82ssZLnAhXYi54KHdZNC_kQjGp6BAgLEDs",
    "places": [
      {
        "position": 1,
        "title": "Nifty Marketing",
        "place_id": "15720806710281841023",
        "lsig": "AB86z5WX2IKpsVSapDNKcS8AYjlj",
        "place_id_search": "https://serpapi.com/search.json?device=desktop&engine=google&google_domain=google.com&lsig=AB86z5WX2IKpsVSapDNKcS8AYjlj&ludocid=15720806710281841023&q=professional+seo+services&tbm=lcl&token=3417fa7c96b09955",
        "rating": 5,
        "reviews": 25,
        "type": "Internet marketing service",
        "hours": "Closed ⋅ Opens 9AM · (877) 795-2249",
        "address": "Burley, ID",
        "website": "https://niftymarketing.com/?utm_source=local&utm_medium=organic&utm_campaign=gmb",
        "description": "\"trustworthy, responsive, and professional. ... Nifty Marketing for a...\"",
        "thumbnail": "data:image/gif;base64,R0lGODlhAQABAIAAAP///////yH5BAEKAAEALAAAAAABAAEAAAICTAEAOw==",
        "gps_coordinates": {
          "latitude": 42.535947,
          "longitude": -113.79363699999999
        }
      },
      {
        "position": 2,
        "title": "Guerrilla SEO Marketing",
        "place_id": "5806900045157705951",
        "lsig": "AB86z5X1WZYteIrHdtOg7ylKyRJU",
        "place_id_search": "https://serpapi.com/search.json?device=desktop&engine=google&google_domain=google.com&lsig=AB86z5X1WZYteIrHdtOg7ylKyRJU&ludocid=5806900045157705951&q=professional+seo+services&tbm=lcl&token=ac3d6f8f0469b4ba",
        "rating": 0,
        "type": "Internet marketing service",
        "address": "Open 24 hours",
        "phone": "(208) 329-8535",
        "gps_coordinates": {
          "latitude": 0,
          "longitude": 0
        }
      },
      {
        "position": 3,
        "title": "OpenPotion Website Design",
        "place_id": "9961635304309978281",
        "lsig": "AB86z5UzKkbwtgN5rRtkT281OkO2",
        "place_id_search": "https://serpapi.com/search.json?device=desktop&engine=google&google_domain=google.com&lsig=AB86z5UzKkbwtgN5rRtkT281OkO2&ludocid=9961635304309978281&q=professional+seo+services&tbm=lcl&token=9bc0495cc66d46e6",
        "rating": 0,
        "type": "Internet marketing service",
        "hours": "(909) 748-5882",
        "address": "Highland, CA",
        "website": "http://www.openpotion.com/",
        "gps_coordinates": {
          "latitude": 42.5512806,
          "longitude": -114.4603243
        }
      }
    ]
  },
  "knowledge_graph": {},
  "related_questions": [
    {
      "question": "What is SEO Service?",
      "snippet": "SEO services (Service Provider) An SEO service provider utilizes the practice of search engine optimization to increase the amount of visitors to a Web site by obtaining high-ranking placements in the search results page of search engines (SERP).",
      "title": "What is SEO Services / SEO Service Provider? Webopedia Definition",
      "link": "https://www.webopedia.com/TERM/S/SEO_services.html",
      "displayed_link": "www.webopedia.com › TERM › SEO_services"
    },
    {
      "question": "How much does SEO cost per month?",
      "snippet": "an average SEO expert charges between $80 and $130 per hour. Further, the average monthly retainer lies somewhere between $750 and $1500 per month. Performance-based SEO is free to start, and has dynamic pricing.",
      "title": "How Much Does SEO Cost? - RankPay",
      "link": "https://www.rankpay.com/seo-cost/",
      "displayed_link": "www.rankpay.com › seo-cost"
    },
    {
      "question": "What is the best SEO company?",
      "snippet": "Best SEO Companies for September 2019Monthly Score: 99.20. Ignite Digital. ... Monthly Score: 97.29. Over The Top SEO. ... Monthly Score: 95.44. Actuate Media. ... Monthly Score: 93.64. SEO Brand. ... Monthly Score: 90.05. SEO Image. ... Monthly Score: 85.58. Mad Fish Digital. ... Monthly Score: 83.68. Rocket Clicks. ... Monthly Score: 78.92. Titan Growth.More items...",
      "title": "Best SEO Companies - Find Best SEO",
      "link": "https://findbestseo.com/awards/10-best-seo-companies",
      "displayed_link": "findbestseo.com › awards › 10-best-seo-companies"
    },
    {
      "question": "Does Google do SEO?",
      "snippet": "Google SEO Guide: The Ultimate Resource Welcome to the Google SEO Guide, your complete, all-in-one guide to ranking competitively in Google's search engine. What is SEO? SEO refers to search engine optimization, or the process of optimizing a website in order to make it easy to find via search engines like Google.",
      "title": "Google SEO Guide: The Ultimate Google SEO Resource",
      "link": "https://www.wordstream.com/google-seo-guide",
      "displayed_link": "www.wordstream.com › google-seo-guide"
    }
  ],
  "organic_results": [
    {
      "position": 1,
      "title": "Professional SEO Services | SEO Services by WebFX",
      "link": "https://www.webfx.com/professional-seo-services.html",
      "displayed_link": "www.webfx.com › professional-seo-services",
      "snippet": "Looking for a professional SEO services provider? Find out why WebFX is the best choice for your business.",
      "cached_page_link": "https://webcache.googleusercontent.com/search?q=cache:gOfx5BfWQyAJ:https://www.webfx.com/professional-seo-services.html+&cd=1&hl=en&ct=clnk&gl=us"
    },
    {
      "position": 2,
      "title": "Professional Search Engine Optimization (SEO) Services ...",
      "link": "https://www.seo.com/seo/",
      "displayed_link": "www.seo.com › seo",
      "snippet": "Get More Website Traffic with Fully Managed, Advanced SEO Services. ... Build your search engine optimization foundation with the trusted experts. ... You can get an edge on the competition with a strong, integrated strategy that combines content marketing, research, technical SEO, social ...",
      "cached_page_link": "https://webcache.googleusercontent.com/search?q=cache:BLMB_QJsbfcJ:https://www.seo.com/seo/+&cd=10&hl=en&ct=clnk&gl=us",
      "related_pages_link": "https://www.google.com/search?q=related:https://www.seo.com/seo/+professional+seo+services&tbo=1&sa=X&ved=2ahUKEwiPh82ssZLnAhXYi54KHdZNC_kQHzAJegQIARAJ"
    },
    {
      "position": 3,
      "title": "Professional SEO Services | SEO Inc",
      "link": "https://www.seoinc.com/professional-seo-services/",
      "displayed_link": "www.seoinc.com › professional-seo-services",
      "snippet": "Since 1997, SEO Inc. has been providing businesses of all sizes with professional SEO services to help increase online visibility. Our proven SEO service ...",
      "cached_page_link": "https://webcache.googleusercontent.com/search?q=cache:gjKSyUBRekAJ:https://www.seoinc.com/professional-seo-services/+&cd=11&hl=en&ct=clnk&gl=us"
    },
    {
      "position": 4,
      "title": "SEO Company | Award-Winning Search Engine Optimization ...",
      "link": "https://thriveagency.com/digital-marketing-services/search-engine-optimization-seo/",
      "displayed_link": "thriveagency.com › Digital Marketing Services",
      "snippet": "You will get to know your Thrive SEO Professional well and they will get to know ... If you're paying us to provide SEO services, shouldn't those services lead to ...",
      "rich_snippet": {
        "top": {
          "detected_extensions": {
            "rating": 4.8,
            "reviews": 146
          },
          "extensions": [
            "Rating: 4.8",
            "146 reviews",
            "Price range: $$"
          ]
        }
      },
      "cached_page_link": "https://webcache.googleusercontent.com/search?q=cache:iUTStYPMbWcJ:https://thriveagency.com/digital-marketing-services/search-engine-optimization-seo/+&cd=12&hl=en&ct=clnk&gl=us"
    },
    {
      "position": 5,
      "title": "#1 Professional Seo services company - Proinseo",
      "link": "https://www.proinseo.com/seo-services/",
      "displayed_link": "www.proinseo.com › seo-services",
      "snippet": "Get #1 Professional seo services company in Uk, USA and worldwide. 900+ Trusted Clients in 2020 and Guarrenteed ranking with the best pro seo services.",
      "cached_page_link": "https://webcache.googleusercontent.com/search?q=cache:xc8KQQk-WC8J:https://www.proinseo.com/seo-services/+&cd=13&hl=en&ct=clnk&gl=us"
    },
    {
      "position": 6,
      "title": "Professional SEO Services USA, Best Local SEO Company ...",
      "link": "https://www.elsner.com/services/seo-services/",
      "displayed_link": "www.elsner.com › services › seo-services",
      "snippet": "Get Professional Seo Services in USA from Elsner to achieve desired results. Visit now to hire best local SEO Company in USA to increase ROI & get ranked on ...",
      "rich_snippet": {
        "bottom": {
          "questions": [
            "How much time does it take to get results from your SEO services?",
            "How do I know whether you are the right company when it comes to SEO services?",
            "Do you offer a monthly SEO package?",
            "What are the different types of reports that I can expect while opting for any of your SEO packages?",
            "What is the cost of carrying out SEO services?"
          ]
        }
      }
    },
    {
      "position": 7,
      "title": "SEO Company - Coalition - 2019's #1 Rated Team",
      "link": "https://coalitiontechnologies.com/",
      "displayed_link": "coalitiontechnologies.com",
      "snippet": "Best ranked and rated SEO company. ... Our Services ... I hold Joel personally in the highest professional regard and would not hesitate to reach out to him on ...",
      "cached_page_link": "https://webcache.googleusercontent.com/search?q=cache:ZhlVAo9iHicJ:https://coalitiontechnologies.com/+&cd=16&hl=en&ct=clnk&gl=us",
      "related_pages_link": "https://www.google.com/search?q=related:https://coalitiontechnologies.com/+professional+seo+services&tbo=1&sa=X&ved=2ahUKEwiPh82ssZLnAhXYi54KHdZNC_kQHzAPegQIAhAH"
    },
    {
      "position": 8,
      "title": "Search Engine Optimization - SEO Services in USA",
      "link": "https://www.firstrankseoservices.com/",
      "displayed_link": "www.firstrankseoservices.com",
      "snippet": "We are the Best SEO Services Company in the USA offering affordable SEO Services with guaranteed organic results. Our professional Search Engine ...",
      "cached_page_link": "https://webcache.googleusercontent.com/search?q=cache:9Ov_0c1u48gJ:https://www.firstrankseoservices.com/+&cd=17&hl=en&ct=clnk&gl=us"
    },
    {
      "position": 9,
      "title": "Professional SEO Services That Work! - SeoServices.com",
      "link": "https://seoservices.com/",
      "displayed_link": "seoservices.com",
      "snippet": "State of the art SEO Services for any niche. We offer Professional SEM, PPC, Social Media Optimization, Content Marketing, Web Design & more.",
      "cached_page_link": "https://webcache.googleusercontent.com/search?q=cache:7F9aITlyGVkJ:https://seoservices.com/+&cd=21&hl=en&ct=clnk&gl=us"
    }
  ],
  "related_searches": [
    {
      "query": "seo services list",
      "link": "https://www.google.com/search?q=seo+services+list&sa=X&ved=2ahUKEwiPh82ssZLnAhXYi54KHdZNC_kQ1QIoAHoECA0QAQ"
    },
    {
      "query": "seo services in usa",
      "link": "https://www.google.com/search?q=seo+services+in+usa&sa=X&ved=2ahUKEwiPh82ssZLnAhXYi54KHdZNC_kQ1QIoAXoECA0QAg"
    },
    {
      "query": "seo agency",
      "link": "https://www.google.com/search?q=seo+agency&sa=X&ved=2ahUKEwiPh82ssZLnAhXYi54KHdZNC_kQ1QIoAnoECA0QAw"
    },
    {
      "query": "seo service provider",
      "link": "https://www.google.com/search?q=seo+service+provider&sa=X&ved=2ahUKEwiPh82ssZLnAhXYi54KHdZNC_kQ1QIoA3oECA0QBA"
    },
    {
      "query": "website seo service",
      "link": "https://www.google.com/search?q=website+seo+service&sa=X&ved=2ahUKEwiPh82ssZLnAhXYi54KHdZNC_kQ1QIoBHoECA0QBQ"
    },
    {
      "query": "seo development services",
      "link": "https://www.google.com/search?q=seo+development+services&sa=X&ved=2ahUKEwiPh82ssZLnAhXYi54KHdZNC_kQ1QIoBXoECA0QBg"
    },
    {
      "query": "seo company",
      "link": "https://www.google.com/search?q=seo+company&sa=X&ved=2ahUKEwiPh82ssZLnAhXYi54KHdZNC_kQ1QIoBnoECA0QBw"
    },
    {
      "query": "webfx seo",
      "link": "https://www.google.com/search?q=webfx+seo&sa=X&ved=2ahUKEwiPh82ssZLnAhXYi54KHdZNC_kQ1QIoB3oECA0QCA"
    }
  ],
  "pagination": {
    "current": 1,
    "next": "https://www.google.com/search?q=professional+seo+services&ei=s7glXs_hJ9iX-gTWm63IDw&start=10&sa=N&ved=2ahUKEwiPh82ssZLnAhXYi54KHdZNC_kQ8NMDegQIEhBD",
    "other_pages": {
      "2": "https://www.google.com/search?q=professional+seo+services&ei=s7glXs_hJ9iX-gTWm63IDw&start=10&sa=N&ved=2ahUKEwiPh82ssZLnAhXYi54KHdZNC_kQ8tMDegQIEhAx",
      "3": "https://www.google.com/search?q=professional+seo+services&ei=s7glXs_hJ9iX-gTWm63IDw&start=20&sa=N&ved=2ahUKEwiPh82ssZLnAhXYi54KHdZNC_kQ8tMDegQIEhAz",
      "4": "https://www.google.com/search?q=professional+seo+services&ei=s7glXs_hJ9iX-gTWm63IDw&start=30&sa=N&ved=2ahUKEwiPh82ssZLnAhXYi54KHdZNC_kQ8tMDegQIEhA1",
      "5": "https://www.google.com/search?q=professional+seo+services&ei=s7glXs_hJ9iX-gTWm63IDw&start=40&sa=N&ved=2ahUKEwiPh82ssZLnAhXYi54KHdZNC_kQ8tMDegQIEhA3",
      "6": "https://www.google.com/search?q=professional+seo+services&ei=s7glXs_hJ9iX-gTWm63IDw&start=50&sa=N&ved=2ahUKEwiPh82ssZLnAhXYi54KHdZNC_kQ8tMDegQIEhA5",
      "7": "https://www.google.com/search?q=professional+seo+services&ei=s7glXs_hJ9iX-gTWm63IDw&start=60&sa=N&ved=2ahUKEwiPh82ssZLnAhXYi54KHdZNC_kQ8tMDegQIEhA7",
      "8": "https://www.google.com/search?q=professional+seo+services&ei=s7glXs_hJ9iX-gTWm63IDw&start=70&sa=N&ved=2ahUKEwiPh82ssZLnAhXYi54KHdZNC_kQ8tMDegQIEhA9",
      "9": "https://www.google.com/search?q=professional+seo+services&ei=s7glXs_hJ9iX-gTWm63IDw&start=80&sa=N&ved=2ahUKEwiPh82ssZLnAhXYi54KHdZNC_kQ8tMDegQIEhA_",
      "10": "https://www.google.com/search?q=professional+seo+services&ei=s7glXs_hJ9iX-gTWm63IDw&start=90&sa=N&ved=2ahUKEwiPh82ssZLnAhXYi54KHdZNC_kQ8tMDegQIEhBB"
    }
  },
  "serpapi_pagination": {
    "current": 1,
    "next_link": "https://serpapi.com/search.json?device=desktop&engine=google&google_domain=google.com&q=professional+seo+services&start=10&token=97f0e9d8ab0c1135",
    "next": "https://serpapi.com/search.json?device=desktop&engine=google&google_domain=google.com&q=professional+seo+services&start=10&token=97f0e9d8ab0c1135",
    "other_pages": {
      "2": "https://serpapi.com/search.json?device=desktop&engine=google&google_domain=google.com&q=professional+seo+services&start=10&token=97f0e9d8ab0c1135",
      "3": "https://serpapi.com/search.json?device=desktop&engine=google&google_domain=google.com&q=professional+seo+services&start=20&token=75b8132d2834d12a",
      "4": "https://serpapi.com/search.json?device=desktop&engine=google&google_domain=google.com&q=professional+seo+services&start=30&token=2f94ef35bbcfffe6",
      "5": "https://serpapi.com/search.json?device=desktop&engine=google&google_domain=google.com&q=professional+seo+services&start=40&token=fa932aeae44121c9",
      "6": "https://serpapi.com/search.json?device=desktop&engine=google&google_domain=google.com&q=professional+seo+services&start=50&token=31e0b2fd39a2177a",
      "7": "https://serpapi.com/search.json?device=desktop&engine=google&google_domain=google.com&q=professional+seo+services&start=60&token=44404f6815616247",
      "8": "https://serpapi.com/search.json?device=desktop&engine=google&google_domain=google.com&q=professional+seo+services&start=70&token=964df724ec2e1083",
      "9": "https://serpapi.com/search.json?device=desktop&engine=google&google_domain=google.com&q=professional+seo+services&start=80&token=860f9e46a35892b3",
      "10": "https://serpapi.com/search.json?device=desktop&engine=google&google_domain=google.com&q=professional+seo+services&start=90&token=169220cae66b9de0"
    }
  }
}