{
  "search_metadata": {
    "id": "",
    "status": "Success",
    "json_endpoint": "",
    "created_at": "2020-01-20 22:32:39 UTC",
    "processed_at": "2020-01-20 22:32:39 UTC",
    "google_url": "https://www.google.com/search?q=solar+energy+ohio&oq=solar+energy+ohio&sourceid=chrome&ie=UTF-8",
    "raw_html_file": "",
    "total_time_taken": 2.13
  },
  "search_parameters": {
    "engine": "google",
    "q": "solar energy ohio",
    "google_domain": "google.com",
    "device": "desktop"
  },
  "search_information": {
    "organic_results_state": "Results for exact spelling",
    "total_results": 25800000,
    "time_taken_displayed": 0.54,
    "query_displayed": "solar energy ohio"
  },
  "ads": [
    {
      "position": 1,
      "block_position": "bottom",
      "title": "Home Solar Panel Systems | No Money Out Of Pocket‎",
      "link": "https://solarspectrum.com/solar-free-quote/",
      "displayed_link": "www.solarspectrum.com/",
      "tracking_link": "https://www.google.com/aclk?sa=l&ai=DChcSEwijsaL0nZPnAhUS02QKHQF3Ae4YABAAGgJwag&sig=AOD64_1UMWcQVhkC6crbY-WRIBX2cLgw9A&q=&ved=2ahUKEwjK-Zv0nZPnAhUZITQIHVvQD7gQ0Qx6BAgTEAE&adurl=",
      "description": "Find Out What You Could Save On Your Energy Bill Today With Solar Spectrum! Custom Designs. Best Solar Technology. Save Energy Costs. Professional Advisors. Types: Buying, Leasing, Financing, Get A Free Quote.",
      "sitelinks": [
        {
          "title": "Free Quote",
          "link": "https://solarspectrum.com/quote/"
        },
        {
          "title": "About Solar Spectrum",
          "link": "https://solarspectrum.com/about-us/"
        },
        {
          "title": "Learn About Solar Energy",
          "link": "https://solarspectrum.com/solar-basics/"
        },
        {
          "title": "Solar Savings",
          "link": "https://solarspectrum.com/savings/"
        }
      ]
    },
    {
      "position": 2,
      "block_position": "bottom",
      "title": "Best & Worst Solar Company | Unbiased Reviews‎",
      "link": "https://bestcompany.com/solar",
      "displayed_link": "www.bestcompany.com/TopSolar/Reviews",
      "tracking_link": "https://www.google.com/aclk?sa=l&ai=DChcSEwijsaL0nZPnAhUS02QKHQF3Ae4YABAFGgJwag&sig=AOD64_1tmyTP4DD-RIxIC7_IAY0eidXZ5g&q=&ved=2ahUKEwjK-Zv0nZPnAhUZITQIHVvQD7gQ0Qx6BAgUEAE&adurl=",
      "description": "Find The Best Solar Providers In California See 6,489+ Reviews Now! Choose Confidently. "
    }
  ],
  "local_map": {
    "link": "https://www.google.com/search?q=solar+energy+ohio&npsic=0&rflfq=1&rldoc=1&rlha=0&rllag=40198121,-83538286,148377&tbm=lcl&sa=X&ved=2ahUKEwjK-Zv0nZPnAhUZITQIHVvQD7gQtgN6BAgMEAQ",
    "image": "data:image/gif;base64,R0lGODlhAQABAIAAAP///////yH5BAEKAAEALAAAAAABAAEAAAICTAEAOw==",
    "gps_coordinates": {
      "latitude": 40.198121,
      "longitude": -83.538286,
      "altitude": 148377
    }
  },
  "local_results": {
    "more_locations_link": "https://www.google.com/search?q=solar+energy+ohio&npsic=0&rflfq=1&rldoc=1&rlha=0&rllag=40198121,-83538286,148377&tbm=lcl&sa=X&ved=2ahUKEwjK-Zv0nZPnAhUZITQIHVvQD7gQjGp6BAgMED4",
    "places": [
      {
        "position": 1,
        "title": "Ohio Power Solutions, LLC",
        "place_id": "7636635158110269240",
        "lsig": "AB86z5VXq82hFddR5vxsPNvNwV9K",
        "place_id_search": "https://serpapi.com/search.json?device=desktop&engine=google&google_domain=google.com&lsig=AB86z5VXq82hFddR5vxsPNvNwV9K&ludocid=7636635158110269240&q=solar+energy+ohio&tbm=lcl&token=c8eeb137a26f1564",
        "rating": 5,
        "reviews": 9,
        "type": "Solar energy equipment supplier",
        "address": "Open ⋅ Closes 7PM",
        "phone": "(740) 908-1040",
        "website": "https://ohiopowersolutions.com/",
        "gps_coordinates": {
          "latitude": 0,
          "longitude": 0
        }
      },
      {
        "position": 2,
        "title": "Edison Solar, Inc.",
        "place_id": "8337242583638538126",
        "lsig": "AB86z5XVK2c7FkE5yMX6PUrUkuC3",
        "place_id_search": "https://serpapi.com/search.json?device=desktop&engine=google&google_domain=google.com&lsig=AB86z5XVK2c7FkE5yMX6PUrUkuC3&ludocid=8337242583638538126&q=solar+energy+ohio&tbm=lcl&token=f6a9b6c61357353a",
        "rating": 5,
        "reviews": 10,
        "type": "Solar energy equipment supplier",
        "hours": "Closed ⋅ Opens 8AM Tue · (419) 499-0000",
        "address": "Milan, OH",
        "website": "http://www.edisonsolar.net/",
        "gps_coordinates": {
          "latitude": 41.3007,
          "longitude": -82.552104
        }
      },
      {
        "position": 3,
        "title": "Solar Energy Solutions",
        "place_id": "10209539460860463029",
        "lsig": "AB86z5XLWuN46UTR9OvEVVS35t9V",
        "place_id_search": "https://serpapi.com/search.json?device=desktop&engine=google&google_domain=google.com&lsig=AB86z5XLWuN46UTR9OvEVVS35t9V&ludocid=10209539460860463029&q=solar+energy+ohio&tbm=lcl&token=3f876a12bdfda005",
        "rating": 5,
        "reviews": 1,
        "type": "Solar energy equipment supplier",
        "hours": "Closed ⋅ Opens 8AM Tue · (513) 400-7340",
        "address": "Cincinnati, OH",
        "website": "http://www.solar-energy-solutions.com/",
        "gps_coordinates": {
          "latitude": 39.0955428,
          "longitude": -84.5244692
        }
      }
    ]
  },
  "knowledge_graph": {
    "see_more_about": []
  },
  "related_questions": [
    {
      "question": "Do solar panels work in Ohio?",
      "snippet": "Indeed, Ohio doesn't get nearly as much sun as Arizona and other hubs for solar energy. ... Central Ohio gets 4 to 5 kilowatt-hours per square meter per day, according to the National Renewable Energy Lab, or NREL. This is a measure of the amount of energy that can be used in photovoltaic panels.Apr 19, 2016",
      "title": "Are rooftop solar panels worthwhile in Ohio? - News - The ...",
      "link": "https://www.dispatch.com/article/20160419/NEWS/304199864",
      "displayed_link": "www.dispatch.com › article › NEWS"
    },
    {
      "question": "How much do solar panels cost in Ohio?",
      "snippet": "What is the current average solar panel cost in Ohio based on current offers? As of September 2019, the average cost of solar panels per watt in Ohio is $3.40/watt. A typical 5000 watt (5 kW) solar system is $16,990 before the federal solar credit and $11,893 after claiming the federal solar tax credit.",
      "title": "Solar Panel Cost in Ohio | Solar-Estimate.org",
      "link": "https://www.solar-estimate.org/solar-panel-cost/ohio",
      "displayed_link": "www.solar-estimate.org › solar-panel-cost › ohio"
    },
    {
      "question": "How much do solar panels cost for a 1500 square foot house?",
      "snippet": "The average homeowner will pay around $20,000 for solar panel installation for the common size needed to power an average 1,500 square foot home. Residential solar panels are usually sized at 3kW to 8kW and can cost between $18,000 and $40,000.",
      "title": "2019 Solar Panel Installation - Cost Guide - Modernize",
      "link": "https://modernize.com/solar/panel-cost-calculator",
      "displayed_link": "modernize.com › solar › panel-cost-calculator"
    },
    {
      "question": "How do I install my own solar panels?",
      "snippet": "The 5 step process to DIY solar panelsDesign and size your system based on energy needs.Purchase your solar equipment (solar panels, inverters, racking)Install the racking or mounts for the panels.Connect the solar panels to your racking equipment.Install a solar inverter.Jun 24, 2019",
      "title": "DIY Solar Pros and Cons: Does it Make Sense for You? | EnergySage",
      "link": "https://news.energysage.com/diy-solar-panels-pros-and-cons/",
      "displayed_link": "news.energysage.com › diy-solar-panels-pros-and-cons"
    }
  ],
  "organic_results": [
    {
      "position": 1,
      "title": "Ohio Solar Panels | 2020 Pricing & Savings | EnergySage",
      "link": "https://www.energysage.com/solar-panels/oh/",
      "displayed_link": "www.energysage.com › solar-panels",
      "date": "Jun 8, 2019",
      "snippet": "What interest is there for solar panels in Ohio and how much can they save you? Check out our list of top solar companies, incentives, and case ...",
      "cached_page_link": "https://webcache.googleusercontent.com/search?q=cache:txMjstkTwp0J:https://www.energysage.com/solar-panels/oh/+&cd=10&hl=en&ct=clnk&gl=us",
      "related_pages_link": "https://www.google.com/search?q=related:https://www.energysage.com/solar-panels/oh/+solar+energy+ohio&tbo=1&sa=X&ved=2ahUKEwjK-Zv0nZPnAhUZITQIHVvQD7gQHzAJegQIAhAJ"
    },
    {
      "position": 2,
      "title": "Ohio solar panels | guide to solar incentives, costs and ...",
      "link": "https://www.solar-estimate.org/solar-panels/ohio",
      "displayed_link": "www.solar-estimate.org › Solar Panels",
      "snippet": "Solar power in Ohio State law requires utilities in the state to offer full retail net metering to their customers. Ohio also has a renewable portfolio standard with a solar carve out, which requires utilities to obtain 12.5% of electricity sold to be derived from renewable energy sources by 2027.",
      "cached_page_link": "https://webcache.googleusercontent.com/search?q=cache:XneNJL1InVgJ:https://www.solar-estimate.org/solar-panels/ohio+&cd=11&hl=en&ct=clnk&gl=us"
    },
    {
      "position": 3,
      "title": "Solar power in Ohio - Wikipedia",
      "link": "https://en.wikipedia.org/wiki/Solar_power_in_Ohio",
      "displayed_link": "en.wikipedia.org › wiki › Solar_power_in_Ohio",
      "snippet": "Ohio installed 10 MW of solar in 2015. ... The First Solar factory in Perrysburg, Ohio can make almost 600 MW of panels per years. Costs have decreased to the point that the average consumer may save approximately $17,527 over a 20-year period by installing solar panels.",
      "sitelinks": {
        "inline": [
          {
            "title": "Solar projects",
            "link": "https://en.wikipedia.org/wiki/Solar_power_in_Ohio#Solar_projects"
          },
          {
            "title": "Toledo area",
            "link": "https://en.wikipedia.org/wiki/Solar_power_in_Ohio#Toledo_area"
          },
          {
            "title": "Dayton",
            "link": "https://en.wikipedia.org/wiki/Solar_power_in_Ohio#Dayton"
          },
          {
            "title": "Renewable portfolio ...",
            "link": "https://en.wikipedia.org/wiki/Solar_power_in_Ohio#Renewable_portfolio_standard"
          }
        ]
      },
      "cached_page_link": "https://webcache.googleusercontent.com/search?q=cache:z-AkRyd9QCQJ:https://en.wikipedia.org/wiki/Solar_power_in_Ohio+&cd=12&hl=en&ct=clnk&gl=us",
      "related_pages_link": "https://www.google.com/search?q=related:https://en.wikipedia.org/wiki/Solar_power_in_Ohio+solar+energy+ohio&tbo=1&sa=X&ved=2ahUKEwjK-Zv0nZPnAhUZITQIHVvQD7gQHzALegQIBRAJ"
    },
    {
      "position": 4,
      "title": "Are rooftop solar panels worthwhile in Ohio? - News - The ...",
      "link": "https://www.dispatch.com/article/20160419/news/304199864",
      "displayed_link": "www.dispatch.com › article › news",
      "date": "Apr 19, 2016",
      "snippet": "On one of the many gray days of an Ohio winter, an observer may wonder whether there is enough sun in the state to make it worthwhile to ...",
      "cached_page_link": "https://webcache.googleusercontent.com/search?q=cache:2jXY6SUP5E0J:https://www.dispatch.com/article/20160419/news/304199864+&cd=13&hl=en&ct=clnk&gl=us"
    },
    {
      "position": 5,
      "title": "Solar Panel Cost 2020 | Current avg. solar system price by Ohio",
      "link": "https://www.solarreviews.com/solar-panels/solar-panel-cost/cost-of-solar-panels-in-ohio",
      "displayed_link": "www.solarreviews.com › Solar Panels › Solar Panel Cost",
      "snippet": "How much do solar panels cost in the average house in Ohio in 2020? As of January 2020, the average cost of solar panels per watt in Ohio is $2.89/watt.",
      "cached_page_link": "https://webcache.googleusercontent.com/search?q=cache:Dg9e99fdV64J:https://www.solarreviews.com/solar-panels/solar-panel-cost/cost-of-solar-panels-in-ohio+&cd=17&hl=en&ct=clnk&gl=us"
    },
    {
      "position": 6,
      "title": "Ohio - Solar Power Rocks",
      "link": "https://www.solarpowerrocks.com/ohio/",
      "displayed_link": "www.solarpowerrocks.com › ohio",
      "snippet": "This page is a complete guide to the complicated and sometimes confusing process of installing solar panels on your Ohio home. Since there's a lot to consider, ...",
      "cached_page_link": "https://webcache.googleusercontent.com/search?q=cache:0WSoIPY73q4J:https://www.solarpowerrocks.com/ohio/+&cd=18&hl=en&ct=clnk&gl=us"
    },
    {
      "position": 7,
      "title": "Solar Power Panels in Ohio: Costs, Companies, and ROI ...",
      "link": "https://decisiondata.org/solar-by-state/ohio/",
      "displayed_link": "decisiondata.org › solar-by-state › ohio",
      "snippet": "Based on the price of electricity in Ohio (an average of 0.12 per kW) and very low amounts of sun (11% less than average) compared to other states, solar power ...",
      "cached_page_link": "https://webcache.googleusercontent.com/search?q=cache:8MIViEziscAJ:https://decisiondata.org/solar-by-state/ohio/+&cd=19&hl=en&ct=clnk&gl=us"
    },
    {
      "position": 8,
      "title": "Ohio Solar | SEIA",
      "link": "https://www.seia.org/state-solar-policy/ohio-solar",
      "displayed_link": "www.seia.org › state-solar-policy › ohio-solar",
      "snippet": "Get facts and figures on the growth of solar energy in Ohio, including companies, projects, and policy resources.",
      "cached_page_link": "https://webcache.googleusercontent.com/search?q=cache:UdHWpf4hmNUJ:https://www.seia.org/state-solar-policy/ohio-solar+&cd=20&hl=en&ct=clnk&gl=us"
    },
    {
      "position": 9,
      "title": "Solar Power in Ohio: All you need to Know! - Solar Nation",
      "link": "https://www.solar-nation.org/ohio",
      "displayed_link": "www.solar-nation.org › ohio",
      "snippet": "Renewable energy, like solar PV, have become something of a political football in Columbus. Which is a real shame, because Ohio certainly isn't lacking in the ...",
      "cached_page_link": "https://webcache.googleusercontent.com/search?q=cache:8MdDrzUMIgEJ:https://www.solar-nation.org/ohio+&cd=21&hl=en&ct=clnk&gl=us"
    },
    {
      "position": 10,
      "title": "Yellowlite: Solar Panels as Alternative Energy For Homes ...",
      "link": "https://www.yellowlite.com/",
      "displayed_link": "www.yellowlite.com",
      "snippet": "YellowLite provides its customers with high-quality solar panels for both ... cloudy reputation discourage you—Ohio gets plenty of sunshine to make solar work.",
      "cached_page_link": "https://webcache.googleusercontent.com/search?q=cache:ToKq6ZaLnM8J:https://www.yellowlite.com/+&cd=22&hl=en&ct=clnk&gl=us"
    }
  ],
  "related_searches": [
    {
      "query": "solar panels ohio grants",
      "link": "https://www.google.com/search?q=solar+panels+ohio+grants&sa=X&ved=2ahUKEwjK-Zv0nZPnAhUZITQIHVvQD7gQ1QIoAHoECA4QAQ"
    },
    {
      "query": "ohio solar incentives 2019",
      "link": "https://www.google.com/search?q=ohio+solar+incentives+2019&sa=X&ved=2ahUKEwjK-Zv0nZPnAhUZITQIHVvQD7gQ1QIoAXoECA4QAg"
    },
    {
      "query": "how much does a solar system cost in ohio?",
      "link": "https://www.google.com/search?q=how+much+does+a+solar+system+cost+in+ohio%3F&sa=X&ved=2ahUKEwjK-Zv0nZPnAhUZITQIHVvQD7gQ1QIoAnoECA4QAw"
    },
    {
      "query": "solar panels cleveland ohio",
      "link": "https://www.google.com/search?q=solar+panels+cleveland+ohio&sa=X&ved=2ahUKEwjK-Zv0nZPnAhUZITQIHVvQD7gQ1QIoA3oECA4QBA"
    },
    {
      "query": "solar panels columbus ohio",
      "link": "https://www.google.com/search?q=solar+panels+columbus+ohio&sa=X&ved=2ahUKEwjK-Zv0nZPnAhUZITQIHVvQD7gQ1QIoBHoECA4QBQ"
    },
    {
      "query": "sign and shine solar program ohio",
      "link": "https://www.google.com/search?q=sign+and+shine+solar+program+ohio&sa=X&ved=2ahUKEwjK-Zv0nZPnAhUZITQIHVvQD7gQ1QIoBXoECA4QBg"
    },
    {
      "query": "ohio renewable energy credits",
      "link": "https://www.google.com/search?q=ohio+renewable+energy+credits&sa=X&ved=2ahUKEwjK-Zv0nZPnAhUZITQIHVvQD7gQ1QIoBnoECA4QBw"
    },
    {
      "query": "solar panels for sale",
      "link": "https://www.google.com/search?q=solar+panels+for+sale&sa=X&ved=2ahUKEwjK-Zv0nZPnAhUZITQIHVvQD7gQ1QIoB3oECA4QCA"
    }
  ],
  "pagination": {
    "current": 1,
    "next": "https://www.google.com/search?q=solar+energy+ohio&ei=iComXsqVNZnC0PEP26C_wAs&start=10&sa=N&ved=2ahUKEwjK-Zv0nZPnAhUZITQIHVvQD7gQ8NMDegQIEhBB",
    "other_pages": {
      "2": "https://www.google.com/search?q=solar+energy+ohio&ei=iComXsqVNZnC0PEP26C_wAs&start=10&sa=N&ved=2ahUKEwjK-Zv0nZPnAhUZITQIHVvQD7gQ8tMDegQIEhAv",
      "3": "https://www.google.com/search?q=solar+energy+ohio&ei=iComXsqVNZnC0PEP26C_wAs&start=20&sa=N&ved=2ahUKEwjK-Zv0nZPnAhUZITQIHVvQD7gQ8tMDegQIEhAx",
      "4": "https://www.google.com/search?q=solar+energy+ohio&ei=iComXsqVNZnC0PEP26C_wAs&start=30&sa=N&ved=2ahUKEwjK-Zv0nZPnAhUZITQIHVvQD7gQ8tMDegQIEhAz",
      "5": "https://www.google.com/search?q=solar+energy+ohio&ei=iComXsqVNZnC0PEP26C_wAs&start=40&sa=N&ved=2ahUKEwjK-Zv0nZPnAhUZITQIHVvQD7gQ8tMDegQIEhA1",
      "6": "https://www.google.com/search?q=solar+energy+ohio&ei=iComXsqVNZnC0PEP26C_wAs&start=50&sa=N&ved=2ahUKEwjK-Zv0nZPnAhUZITQIHVvQD7gQ8tMDegQIEhA3",
      "7": "https://www.google.com/search?q=solar+energy+ohio&ei=iComXsqVNZnC0PEP26C_wAs&start=60&sa=N&ved=2ahUKEwjK-Zv0nZPnAhUZITQIHVvQD7gQ8tMDegQIEhA5",
      "8": "https://www.google.com/search?q=solar+energy+ohio&ei=iComXsqVNZnC0PEP26C_wAs&start=70&sa=N&ved=2ahUKEwjK-Zv0nZPnAhUZITQIHVvQD7gQ8tMDegQIEhA7",
      "9": "https://www.google.com/search?q=solar+energy+ohio&ei=iComXsqVNZnC0PEP26C_wAs&start=80&sa=N&ved=2ahUKEwjK-Zv0nZPnAhUZITQIHVvQD7gQ8tMDegQIEhA9",
      "10": "https://www.google.com/search?q=solar+energy+ohio&ei=iComXsqVNZnC0PEP26C_wAs&start=90&sa=N&ved=2ahUKEwjK-Zv0nZPnAhUZITQIHVvQD7gQ8tMDegQIEhA_"
    }
  },
  "serpapi_pagination": {
    "current": 1,
    "next_link": "https://serpapi.com/search.json?device=desktop&engine=google&google_domain=google.com&q=solar+energy+ohio&start=10&token=246717763d18325f",
    "next": "https://serpapi.com/search.json?device=desktop&engine=google&google_domain=google.com&q=solar+energy+ohio&start=10&token=246717763d18325f",
    "other_pages": {
      "2": "https://serpapi.com/search.json?device=desktop&engine=google&google_domain=google.com&q=solar+energy+ohio&start=10&token=246717763d18325f",
      "3": "https://serpapi.com/search.json?device=desktop&engine=google&google_domain=google.com&q=solar+energy+ohio&start=20&token=5cd0b6b952132140",
      "4": "https://serpapi.com/search.json?device=desktop&engine=google&google_domain=google.com&q=solar+energy+ohio&start=30&token=db1b183a595cabc4",
      "5": "https://serpapi.com/search.json?device=desktop&engine=google&google_domain=google.com&q=solar+energy+ohio&start=40&token=2e8c9075b230a8bb",
      "6": "https://serpapi.com/search.json?device=desktop&engine=google&google_domain=google.com&q=solar+energy+ohio&start=50&token=fa8a05c3e51898c1",
      "7": "https://serpapi.com/search.json?device=desktop&engine=google&google_domain=google.com&q=solar+energy+ohio&start=60&token=e2e97294ab95102b",
      "8": "https://serpapi.com/search.json?device=desktop&engine=google&google_domain=google.com&q=solar+energy+ohio&start=70&token=3dbeac9143465ba8",
      "9": "https://serpapi.com/search.json?device=desktop&engine=google&google_domain=google.com&q=solar+energy+ohio&start=80&token=edd688d380d69786",
      "10": "https://serpapi.com/search.json?device=desktop&engine=google&google_domain=google.com&q=solar+energy+ohio&start=90&token=c8f35de3d092e1ce"
    }
  }
}